jsb/__init__.py
jsb/generic.py
jsb/primitives.py
jsb/schema.py
jsonschema_builder-0.1.1.dist-info/DESCRIPTION.rst
jsonschema_builder-0.1.1.dist-info/METADATA
jsonschema_builder-0.1.1.dist-info/RECORD
jsonschema_builder-0.1.1.dist-info/WHEEL
jsonschema_builder-0.1.1.dist-info/metadata.json
jsonschema_builder-0.1.1.dist-info/top_level.txt
tests/__init__.py
tests/test_functional.py
tests/test_generic.py
tests/test_primitives.py
tests/test_schema.py
