Metadata-Version: 2.0
Name: jsonschema-builder
Version: 0.1.1
Summary: JSON Schema builder
Home-page: https://git.link-society.com/link-society/jsonschema-builder
Author: Link Society
Author-email: contact@link-society.com
License: Apache
Keywords: json schema
Platform: UNKNOWN
Classifier: Development Status :: 3 - Alpha
Classifier: Operating System :: OS Independent
Classifier: Programming Language :: Python
Classifier: Programming Language :: Python :: 3
Classifier: Programming Language :: Python :: 3.4
Classifier: Programming Language :: Python :: 3.5
Classifier: Programming Language :: Python :: 3.6
Classifier: Programming Language :: Python :: Implementation :: CPython
Requires-Dist: addict (>=2.1.2)
Requires-Dist: pytest-runner (>=3.0)
